freecrawl/__init__.py
freecrawl/__main__.py
freecrawl/server.py
freecrawl_mcp-0.1.2.dist-info/METADATA
freecrawl_mcp-0.1.2.dist-info/WHEEL
freecrawl_mcp-0.1.2.dist-info/entry_points.txt
freecrawl_mcp-0.1.2.dist-info/RECORD
