Metadata-Version: 2.4
Name: freecrawl-mcp
Version: 0.1.2
Summary: FreeCrawl MCP Server - Self-hosted web scraping and document processing as a Firecrawl replacement
Project-URL: Homepage, https://github.com/dylan-gluck/freecrawl-mcp
Project-URL: Repository, https://github.com/dylan-gluck/freecrawl-mcp
Project-URL: Issues, https://github.com/dylan-gluck/freecrawl-mcp/issues
Author-email: Dylan Gluck <dylan@dylangluck.com>
License: MIT
Keywords: document-processing,firecrawl,mcp,playwright,web-scraping
Classifier: Development Status :: 4 - Beta
Classifier: Intended Audience :: Developers
Classifier: License :: OSI Approved :: MIT License
Classifier: Programming Language :: Python :: 3
Classifier: Programming Language :: Python :: 3.12
Classifier: Topic :: Internet :: WWW/HTTP :: Browsers
Classifier: Topic :: Software Development :: Libraries :: Python Modules
Requires-Python: >=3.12
Requires-Dist: aiohttp>=3.9.0
Requires-Dist: aiosqlite>=0.19.0
Requires-Dist: beautifulsoup4>=4.12.0
Requires-Dist: markdownify>=0.11.0
Requires-Dist: mcp>=1.0.0
Requires-Dist: playwright>=1.40.0
Requires-Dist: psutil>=5.9.0
Requires-Dist: pydantic>=2.0.0
Requires-Dist: tenacity>=8.0.0
